{"metadata":{},"options":{"plugins":[{"key":"base$1$0","visitor":{"_exploded":{},"_verified":{},"JSXNamespacedName":{"enter":[null]},"JSXElement":{"exit":[null]},"JSXFragment":{"exit":[null]},"Program":{"enter":[null],"exit":[null]},"JSXAttribute":{"enter":[null]}},"options":{"pragma":"React.createElement","pragmaFrag":"React.Fragment","throwIfNamespace":true,"useBuiltIns":false}},{"key":"base$1$1","visitor":{"_exploded":true,"_verified":true},"options":{}},{"key":"base$1$2","visitor":{"ExportDefaultDeclaration":{"enter":[null]},"CallExpression":{"enter":[null]},"_exploded":true,"_verified":true},"options":{}},{"key":"base$0$0","visitor":{"Program":{"enter":[null]},"_exploded":true,"_verified":true},"options":{"generateLetDeclarations":true,"enforceStrictMode":false}},{"key":"base$0$1","visitor":{"_exploded":true,"_verified":true},"options":{}},{"key":"base$0$2","visitor":{"_exploded":{},"_verified":{},"Program":{"enter":[null]},"ImportDeclaration":{"enter":[null,null]},"ClassProperty":{"enter":[null]},"AssignmentPattern":{"enter":[null]},"TypeCastExpression":{"enter":[null,null]},"ImportSpecifier":{"enter":[null]},"ClassDeclaration":{"enter":[null]},"ClassExpression":{"enter":[null]},"FunctionDeclaration":{"enter":[null]},"FunctionExpression":{"enter":[null]},"ObjectMethod":{"enter":[null]},"ArrowFunctionExpression":{"enter":[null]},"ClassMethod":{"enter":[null]},"AnyTypeAnnotation":{"enter":[null]},"ArrayTypeAnnotation":{"enter":[null]},"BooleanTypeAnnotation":{"enter":[null]},"BooleanLiteralTypeAnnotation":{"enter":[null]},"NullLiteralTypeAnnotation":{"enter":[null]},"ClassImplements":{"enter":[null]},"DeclareClass":{"enter":[null]},"DeclareFunction":{"enter":[null]},"DeclareInterface":{"enter":[null]},"DeclareModule":{"enter":[null]},"DeclareModuleExports":{"enter":[null]},"DeclareTypeAlias":{"enter":[null]},"DeclareOpaqueType":{"enter":[null]},"DeclareVariable":{"enter":[null]},"DeclareExportDeclaration":{"enter":[null]},"DeclareExportAllDeclaration":{"enter":[null]},"DeclaredPredicate":{"enter":[null]},"ExistsTypeAnnotation":{"enter":[null]},"FunctionTypeAnnotation":{"enter":[null]},"FunctionTypeParam":{"enter":[null]},"GenericTypeAnnotation":{"enter":[null]},"InferredPredicate":{"enter":[null]},"InterfaceExtends":{"enter":[null]},"InterfaceDeclaration":{"enter":[null]},"IntersectionTypeAnnotation":{"enter":[null]},"MixedTypeAnnotation":{"enter":[null]},"EmptyTypeAnnotation":{"enter":[null]},"NullableTypeAnnotation":{"enter":[null]},"NumberLiteralTypeAnnotation":{"enter":[null]},"NumberTypeAnnotation":{"enter":[null]},"ObjectTypeAnnotation":{"enter":[null]},"ObjectTypeCallProperty":{"enter":[null]},"ObjectTypeIndexer":{"enter":[null]},"ObjectTypeProperty":{"enter":[null]},"ObjectTypeSpreadProperty":{"enter":[null]},"OpaqueType":{"enter":[null]},"QualifiedTypeIdentifier":{"enter":[null]},"StringLiteralTypeAnnotation":{"enter":[null]},"StringTypeAnnotation":{"enter":[null]},"ThisTypeAnnotation":{"enter":[null]},"TupleTypeAnnotation":{"enter":[null]},"TypeofTypeAnnotation":{"enter":[null]},"TypeAlias":{"enter":[null]},"TypeAnnotation":{"enter":[null]},"TypeParameter":{"enter":[null]},"TypeParameterDeclaration":{"enter":[null]},"TypeParameterInstantiation":{"enter":[null]},"UnionTypeAnnotation":{"enter":[null]},"Variance":{"enter":[null]},"VoidTypeAnnotation":{"enter":[null]},"ExportAllDeclaration":{"enter":[null]},"ExportDefaultDeclaration":{"enter":[null]},"ExportNamedDeclaration":{"enter":[null]}},"options":{}},{"key":"base$0$3","visitor":{"CallExpression":{"enter":[null]},"BinaryExpression":{"enter":[null]},"MemberExpression":{"enter":[null],"exit":[null]},"_exploded":true,"_verified":true,"Identifier":{"enter":[null]},"JSXIdentifier":{"enter":[null]}},"options":{"polyfill":false,"useBuiltIns":true}},{"key":"base$0$4","visitor":{"_exploded":true,"_verified":true},"options":{}},{"key":"base$0$5","visitor":{"_exploded":{},"_verified":{},"VariableDeclarator":{"enter":[null]},"ExportNamedDeclaration":{"enter":[null]},"CatchClause":{"enter":[null]},"AssignmentExpression":{"enter":[null]},"ObjectExpression":{"enter":[null]},"FunctionDeclaration":{"enter":[null]},"FunctionExpression":{"enter":[null]},"ObjectMethod":{"enter":[null]},"ArrowFunctionExpression":{"enter":[null]},"ClassMethod":{"enter":[null]},"ForInStatement":{"enter":[null]},"ForOfStatement":{"enter":[null]}},"options":{}},{"key":"transform-meteor-async-await","visitor":{"AwaitExpression":{"enter":[null]},"_exploded":true,"_verified":true,"FunctionDeclaration":{"exit":[null]},"FunctionExpression":{"exit":[null]},"ObjectMethod":{"exit":[null]},"ArrowFunctionExpression":{"exit":[null]},"ClassMethod":{"exit":[null]}},"options":{"useNativeAsyncAwait":false}},{"key":"transform-meteor-dynamic-import","visitor":{"_exploded":{},"_verified":{},"CallExpression":{"enter":[null]}},"options":{}},{"key":"base$0$8","visitor":{"_exploded":{},"_verified":{},"Program":{"enter":[null]}},"options":{}},{"key":"base$0$9","visitor":{"Program":{"exit":[null]},"_exploded":true,"_verified":true},"options":{"allowTopLevelThis":true,"strictMode":false,"loose":true}},{"key":"base$0$10","visitor":{"_exploded":{},"_verified":{},"ClassDeclaration":{"enter":[null]},"ClassExpression":{"enter":[null]}},"options":{"loose":true}}],"compact":false,"ast":true,"babelrc":false,"sourceFileName":"imports/plugins/core/graphql/server/index.js","filename":"imports/plugins/core/graphql/server/index.js","sourceMaps":true,"envName":"development","cwd":"/Users/estebandev/test-knowledge","passPerPreset":false,"presets":[],"parserOpts":{"sourceType":"module","sourceFileName":"imports/plugins/core/graphql/server/index.js","plugins":["jsx","jsx","flow","flow","objectRestSpread","objectRestSpread","dynamicImport","asyncGenerators","classProperties"]},"generatorOpts":{"filename":"imports/plugins/core/graphql/server/index.js","comments":true,"compact":false,"sourceMaps":true,"sourceFileName":"imports/plugins/core/graphql/server/index.js"}},"code":"let Meteor;\nmodule.watch(require(\"meteor/meteor\"), {\n  Meteor(v) {\n    Meteor = v;\n  }\n\n}, 0);\nlet MongoInternals;\nmodule.watch(require(\"meteor/mongo\"), {\n  MongoInternals(v) {\n    MongoInternals = v;\n  }\n\n}, 1);\nlet WebApp;\nmodule.watch(require(\"meteor/webapp\"), {\n  WebApp(v) {\n    WebApp = v;\n  }\n\n}, 2);\nlet createApolloServer;\nmodule.watch(require(\"./createApolloServer\"), {\n  default(v) {\n    createApolloServer = v;\n  }\n\n}, 3);\nlet defineCollections;\nmodule.watch(require(\"./defineCollections\"), {\n  default(v) {\n    defineCollections = v;\n  }\n\n}, 4);\nlet methods;\nmodule.watch(require(\"./methods\"), {\n  default(v) {\n    methods = v;\n  }\n\n}, 5);\nlet queries;\nmodule.watch(require(\"./queries\"), {\n  default(v) {\n    queries = v;\n  }\n\n}, 6);\nconst collections = {};\nconst {\n  db\n} = MongoInternals.defaultRemoteCollectionDriver().mongo;\ndefineCollections(db, collections);\nconst server = createApolloServer({\n  context: {\n    collections,\n    methods,\n    queries\n  },\n  // XXX Eventually these should be from individual env variables instead\n  debug: Meteor.isDevelopment,\n  graphiql: Meteor.isDevelopment\n}); // bind the specified paths to the Express server running Apollo + GraphiQL\n\nWebApp.connectHandlers.use(server);","map":{"version":3,"sources":["imports/plugins/core/graphql/server/index.js"],"names":["Meteor","module","watch","require","v","MongoInternals","WebApp","createApolloServer","default","defineCollections","methods","queries","collections","db","defaultRemoteCollectionDriver","mongo","server","context","debug","isDevelopment","graphiql","connectHandlers","use"],"mappings":"AAAA,IAAIA,MAAJ;AAAWC,OAAOC,KAAP,CAAaC,QAAQ,eAAR,CAAb,EAAsC;AAACH,SAAOI,CAAP,EAAS;AAACJ,aAAOI,CAAP;AAAS;;AAApB,CAAtC,EAA4D,CAA5D;AAA+D,IAAIC,cAAJ;AAAmBJ,OAAOC,KAAP,CAAaC,QAAQ,cAAR,CAAb,EAAqC;AAACE,iBAAeD,CAAf,EAAiB;AAACC,qBAAeD,CAAf;AAAiB;;AAApC,CAArC,EAA2E,CAA3E;AAA8E,IAAIE,MAAJ;AAAWL,OAAOC,KAAP,CAAaC,QAAQ,eAAR,CAAb,EAAsC;AAACG,SAAOF,CAAP,EAAS;AAACE,aAAOF,CAAP;AAAS;;AAApB,CAAtC,EAA4D,CAA5D;AAA+D,IAAIG,kBAAJ;AAAuBN,OAAOC,KAAP,CAAaC,QAAQ,sBAAR,CAAb,EAA6C;AAACK,UAAQJ,CAAR,EAAU;AAACG,yBAAmBH,CAAnB;AAAqB;;AAAjC,CAA7C,EAAgF,CAAhF;AAAmF,IAAIK,iBAAJ;AAAsBR,OAAOC,KAAP,CAAaC,QAAQ,qBAAR,CAAb,EAA4C;AAACK,UAAQJ,CAAR,EAAU;AAACK,wBAAkBL,CAAlB;AAAoB;;AAAhC,CAA5C,EAA8E,CAA9E;AAAiF,IAAIM,OAAJ;AAAYT,OAAOC,KAAP,CAAaC,QAAQ,WAAR,CAAb,EAAkC;AAACK,UAAQJ,CAAR,EAAU;AAACM,cAAQN,CAAR;AAAU;;AAAtB,CAAlC,EAA0D,CAA1D;AAA6D,IAAIO,OAAJ;AAAYV,OAAOC,KAAP,CAAaC,QAAQ,WAAR,CAAb,EAAkC;AAACK,UAAQJ,CAAR,EAAU;AAACO,cAAQP,CAAR;AAAU;;AAAtB,CAAlC,EAA0D,CAA1D;AAQ3hB,MAAMQ,cAAc,EAApB;AAEA,MAAM;AAAEC;AAAF,IAASR,eAAeS,6BAAf,GAA+CC,KAA9D;AACAN,kBAAkBI,EAAlB,EAAsBD,WAAtB;AAEA,MAAMI,SAAST,mBAAmB;AAChCU,WAAS;AACPL,eADO;AAEPF,WAFO;AAGPC;AAHO,GADuB;AAMhC;AACAO,SAAOlB,OAAOmB,aAPkB;AAQhCC,YAAUpB,OAAOmB;AARe,CAAnB,CAAf,C,CAWA;;AACAb,OAAOe,eAAP,CAAuBC,GAAvB,CAA2BN,MAA3B","sourcesContent":["import { Meteor } from \"meteor/meteor\";\nimport { MongoInternals } from \"meteor/mongo\";\nimport { WebApp } from \"meteor/webapp\";\nimport createApolloServer from \"./createApolloServer\";\nimport defineCollections from \"./defineCollections\";\nimport methods from \"./methods\";\nimport queries from \"./queries\";\n\nconst collections = {};\n\nconst { db } = MongoInternals.defaultRemoteCollectionDriver().mongo;\ndefineCollections(db, collections);\n\nconst server = createApolloServer({\n  context: {\n    collections,\n    methods,\n    queries\n  },\n  // XXX Eventually these should be from individual env variables instead\n  debug: Meteor.isDevelopment,\n  graphiql: Meteor.isDevelopment\n});\n\n// bind the specified paths to the Express server running Apollo + GraphiQL\nWebApp.connectHandlers.use(server);\n"]},"sourceType":"script","hash":"586e02dee7bda1675cfbc224f044bfba5d2709c6"}
